sortedmultiset/__init__.py
sortedmultiset/sortedmultiset.py
sortedmultiset-1.1.1.dist-info/LICENSE
sortedmultiset-1.1.1.dist-info/METADATA
sortedmultiset-1.1.1.dist-info/WHEEL
sortedmultiset-1.1.1.dist-info/top_level.txt
sortedmultiset-1.1.1.dist-info/RECORD
