Metadata-Version: 2.1
Name: sortedmultiset
Version: 1.1.1
Summary: A sorted multiset which is similar to multiset of cpp so can developers access,delete,search elements in O(log n) time which can make job easy.Helpful for coders.
Author: Rushikesh Sunil Kotkar
Author-email: Rushikesh Sunil Kotkar <rshksh019@gmail.com>
Project-URL: Homepage, https://github.com/rishiko/sortedmultiset
Project-URL: Issues, https://github.com/rishiko/sortedmultiset/blob/main/User%20Guide
Keywords: python,multiset
Classifier: Programming Language :: Python :: 3
Classifier: License :: OSI Approved :: MIT License
Classifier: Operating System :: OS Independent
Requires-Python: >=3.0.0
License-File: LICENSE
